roteiro_1/disp7.vhd
library IEEE;
use IEEE.STD_LOGIC_1164.ALL;
ENTITY disp7 IS
PORT (dec : IN STD_LOGIC_VECTOR (3 DOWNTO 0);
	disp : OUT STD_LOGIC_VECTOR (6 DOWNTO 0));
END disp7;

ARCHITECTURE decod OF disp7 IS
BEGIN
	with dec select
	disp <= "1111001" when "0001", --1
	"0100100" when "0010", --2
	"0110000" when "0011", --3
	"0011001" when "0100", --4
	"0010010" when "0101", --5
	"0000010" when "0110", --6
	"1111000" when "0111", --7
	"0000000" when "1000", --8
	"0010000" when "1001", --9
	"0001000" when "1010", --A
	"0000011" when "1011", --b
	"1000110" when "1100", --C
	"0100001" when "1101", --d
	"0000110" when "1110", --E
	"0001110" when "1111", --F
	"1000000" when others; --0
END decod;

roteiro_1/conta.vhd
LIBRARY IEEE;
USE IEEE.STD_LOGIC_1164.ALL;
USE IEEE.NUMERIC_STD.ALL;
USE IEEE.MATH_REAL.ALL;

ENTITY conta IS
	PORT ( ckin : IN STD_LOGIC;
	vcont : OUT STD_LOGIC_VECTOR (3 DOWNTO 0);
	ckout : OUT STD_LOGIC);
END conta;

ARCHITECTURE soma OF conta IS
	SIGNAL vcont_s : STD_LOGIC_VECTOR (3 DOWNTO 0) := "0000";
	SIGNAL max : STD_LOGIC_VECTOR (3 DOWNTO 0) := "1001";
	SIGNAL ckout_s : STD_LOGIC := '0';
BEGIN
	vcont <= vcont_s ;
	ckout <= ckout_s;
	PROCESS (ckin)
	BEGIN
		IF ckin'EVENT and ckin = '0' THEN
			IF vcont_s /= max THEN
				vcont_s <= std_logic_vector(unsigned(vcont_s) + 1);
				ckout_s <= '1';
			ELSE
				vcont_s <= "0000";
				ckout_s <= '0';
			END IF;
		END IF;
	END PROCESS;
END soma;

roteiro_1/contador99.vhd
LIBRARY ieee;
USE ieee.std_logic_1164.all;
ENTITY contador99 IS
PORT
( ck : IN STD_LOGIC;
	hex0 : OUT STD_LOGIC_VECTOR(6 DOWNTO 0);
	hex1 : OUT STD_LOGIC_VECTOR(6 DOWNTO 0);
	hex2 : OUT STD_LOGIC_VECTOR(6 DOWNTO 0)
);
END contador99;

ARCHITECTURE contagem OF contador99 IS
COMPONENT conta
	PORT(ckin : IN STD_LOGIC;
	ckout : OUT STD_LOGIC;
	--ckoutdez : OUT STD_LOGIC;
	vcont : OUT STD_LOGIC_VECTOR(3 DOWNTO 0));
END COMPONENT;

COMPONENT disp7
PORT(
	dec : IN STD_LOGIC_VECTOR(3 DOWNTO 0);
	disp : OUT STD_LOGIC_VECTOR(6 DOWNTO 0)
);

END COMPONENT;

SIGNAL ckdez : STD_LOGIC;
SIGNAL ckcent : STD_LOGIC;
SIGNAL cent : STD_LOGIC_VECTOR(3 DOWNTO 0);
SIGNAL dez : STD_LOGIC_VECTOR(3 DOWNTO 0);
SIGNAL uni : STD_LOGIC_VECTOR(3 DOWNTO 0);

BEGIN
	conta_uni : conta
	PORT MAP(ckin => ck,
	ckout => ckdez,
	vcont => uni);

	conta_dez : conta
	PORT MAP(ckin => ckdez,
	ckout => ckcent,
	vcont => dez);
	
	conta_cent : conta
	PORT MAP(ckin => ckcent,
	vcont => cent);

	disp_uni : disp7
	PORT MAP(dec => uni,
	disp => hex2);

	disp_dez : disp7
	PORT MAP(dec => dez,
	disp => hex1);

	disp_cent : disp7
	PORT MAP (dec => cent,
	disp => hex0);

END contagem;

roteiro_1/testbench.vhd
library IEEE;
use IEEE.STD_LOGIC_1164.ALL;
use std.textio.all;
--use IEEE.numeric_std.all;


ENTITY testbench is
END testbench;

ARCHITECTURE behavioral OF testbench IS
	COMPONENT contador99 
		PORT 
		(
			ck : IN STD_LOGIC;
			hex0 : OUT STD_LOGIC_VECTOR(6 DOWNTO 0);
			hex1 : OUT STD_LOGIC_VECTOR(6 DOWNTO 0);
			hex2 : OUT STD_LOGIC_VECTOR(6 DOWNTO 0)
		);
	END COMPONENT;

-- input
SIGNAL ck : STD_LOGIC := '0';
CONSTANT clk_period : TIME := 1 ms;
-- output
SIGNAL hex0 :  STD_LOGIC_VECTOR(6 DOWNTO 0);
SIGNAL hex1 :  STD_LOGIC_VECTOR(6 DOWNTO 0);
SIGNAL hex2 :  STD_LOGIC_VECTOR(6 DOWNTO 0);

FUNCTION decoder(i : IN STD_LOGIC_VECTOR(6 DOWNTO 0) := "0000000")
	return string is
	VARIABLE output : string(1 to 4);
BEGIN
	-- Verifica a saída no display de 7 segmentos e define a saída correspondente
	CASE i IS
		WHEN "1000000" => output := "0x40";
		WHEN "1111001" => output := "0x79";
		WHEN "0100100" => output := "0x24";
		WHEN others => output := "0xXX";
		return output;
	END CASE;
	return output;
END FUNCTION;

BEGIN

inst : contador99 PORT MAP (
	ck => ck,
	hex0 => hex0,
	hex1 => hex1,
	hex2 => hex2
);

-- Processo que realiza a escrita de output para um arquivo
salva_dados : PROCESS(ck)
	file arquivo : text open write_mode is "/home/demo/saida.dat";
	variable linha : line;
	variable dado : string(1 to 4);
	BEGIN
		IF RISING_EDGE(ck) THEN
			dado := decoder(hex2);
			write(linha, dado);
			--hwrite(linha, hex2); -- Use for debug
			writeline(arquivo, linha);
		END IF;
	END PROCESS;
ck <= NOT ck after clk_period/2;	

END behavioral;

roteiro_1/testbench.vcd
$date
  Fri Apr 22 12:40:47 2022
$end
$version
  GHDL v0
$end
$timescale
  1 fs
$end
$scope module standard $end
$upscope $end
$scope module std_logic_1164 $end
$upscope $end
$scope module textio $end
$upscope $end
$scope module numeric_std $end
$upscope $end
$scope module math_real $end
$upscope $end
$scope module testbench $end
$var reg 1 ! ck $end
$var reg 7 " hex0[6:0] $end
$var reg 7 # hex1[6:0] $end
$var reg 7 $ hex2[6:0] $end
$scope module inst $end
$var reg 1 % ck $end
$var reg 7 & hex0[6:0] $end
$var reg 7 ' hex1[6:0] $end
$var reg 7 ( hex2[6:0] $end
$var reg 1 ) ckdez $end
$var reg 1 * ckcent $end
$var reg 4 + cent[3:0] $end
$var reg 4 , dez[3:0] $end
$var reg 4 - uni[3:0] $end
$scope module conta_uni $end
$var reg 1 . ckin $end
$var reg 4 / vcont[3:0] $end
$var reg 1 0 ckout $end
$var reg 4 1 vcont_s[3:0] $end
$var reg 4 2 max[3:0] $end
$var reg 1 3 ckout_s $end
$upscope $end
$scope module conta_dez $end
$var reg 1 4 ckin $end
$var reg 4 5 vcont[3:0] $end
$var reg 1 6 ckout $end
$var reg 4 7 vcont_s[3:0] $end
$var reg 4 8 max[3:0] $end
$var reg 1 9 ckout_s $end
$upscope $end
$scope module conta_cent $end
$var reg 1 : ckin $end
$var reg 4 ; vcont[3:0] $end
$var reg 1 < ckout $end
$var reg 4 = vcont_s[3:0] $end
$var reg 4 > max[3:0] $end
$var reg 1 ? ckout_s $end
$upscope $end
$scope module disp_uni $end
$var reg 4 @ dec[3:0] $end
$var reg 7 A disp[6:0] $end
$upscope $end
$scope module disp_dez $end
$var reg 4 B dec[3:0] $end
$var reg 7 C disp[6:0] $end
$upscope $end
$scope module disp_cent $end
$var reg 4 D dec[3:0] $end
$var reg 7 E disp[6:0] $end
$upscope $end
$upscope $end
$upscope $end
$enddefinitions $end
#0
0!
b1000000 "
b1000000 #
b1000000 $
0%
b1000000 &
b1000000 '
b1000000 (
0)
0*
b0000 +
b0000 ,
b0000 -
0.
b0000 /
00
b0000 1
b1001 2
03
04
b0000 5
06
b0000 7
b1001 8
09
0:
b0000 ;
0<
b0000 =
b1001 >
0?
b0000 @
b1000000 A
b0000 B
b1000000 C
b0000 D
b1000000 E
#500000000000
1!
b1111001 $
1%
b1111001 (
b0001 -
1.
b0001 /
b0001 1
b0001 @
b1111001 A
#1000000000000
0!
0%
0.
#1500000000000
1!
b0100100 $
1%
b0100100 (
b0010 -
1.
b0010 /
b0010 1
b0010 @
b0100100 A
#2000000000000
0!
0%
0.
#2500000000000
1!
b0110000 $
1%
b0110000 (
b0011 -
1.
b0011 /
b0011 1
b0011 @
b0110000 A
#3000000000000
0!
0%
0.
#3500000000000
1!
b0011001 $
1%
b0011001 (
b0100 -
1.
b0100 /
b0100 1
b0100 @
b0011001 A
#4000000000000
0!
0%
0.
#4500000000000
1!
b0010010 $
1%
b0010010 (
b0101 -
1.
b0101 /
b0101 1
b0101 @
b0010010 A
#5000000000000
0!
0%
0.
#5500000000000
1!
b0000010 $
1%
b0000010 (
b0110 -
1.
b0110 /
b0110 1
b0110 @
b0000010 A
#6000000000000
0!
0%
0.
#6500000000000
1!
b1111000 $
1%
b1111000 (
b0111 -
1.
b0111 /
b0111 1
b0111 @
b1111000 A
#7000000000000
0!
0%
0.
#7500000000000
1!
b0000000 $
1%
b0000000 (
b1000 -
1.
b1000 /
b1000 1
b1000 @
b0000000 A
#8000000000000
0!
0%
0.
#8500000000000
1!
b0010000 $
1%
b0010000 (
b1001 -
1.
b1001 /
b1001 1
b1001 @
b0010000 A
#9000000000000
0!
0%
0.
#9500000000000
1!
b1111001 #
b1000000 $
1%
b1111001 '
b1000000 (
1)
b0001 ,
b0000 -
1.
b0000 /
10
b0000 1
13
14
b0001 5
b0001 7
b0000 @
b1000000 A
b0001 B
b1111001 C
#10000000000000
0!
0%
0.
#10500000000000
1!
b1111001 $
1%
b1111001 (
0)
b0001 -
1.
b0001 /
00
b0001 1
03
04
b0001 @
b1111001 A
#11000000000000
0!
0%
0.
#11500000000000
1!
b0100100 $
1%
b0100100 (
b0010 -
1.
b0010 /
b0010 1
b0010 @
b0100100 A
#12000000000000
0!
0%
0.
#12500000000000
1!
b0110000 $
1%
b0110000 (
b0011 -
1.
b0011 /
b0011 1
b0011 @
b0110000 A
#13000000000000
0!
0%
0.
#13500000000000
1!
b0011001 $
1%
b0011001 (
b0100 -
1.
b0100 /
b0100 1
b0100 @
b0011001 A
#14000000000000
0!
0%
0.
#14500000000000
1!
b0010010 $
1%
b0010010 (
b0101 -
1.
b0101 /
b0101 1
b0101 @
b0010010 A
#15000000000000
0!
0%
0.
#15500000000000
1!
b0000010 $
1%
b0000010 (
b0110 -
1.
b0110 /
b0110 1
b0110 @
b0000010 A
#16000000000000
0!
0%
0.
#16500000000000
1!
b1111000 $
1%
b1111000 (
b0111 -
1.
b0111 /
b0111 1
b0111 @
b1111000 A
#17000000000000
0!
0%
0.
#17500000000000
1!
b0000000 $
1%
b0000000 (
b1000 -
1.
b1000 /
b1000 1
b1000 @
b0000000 A
#18000000000000
0!
0%
0.
#18500000000000
1!
b0010000 $
1%
b0010000 (
b1001 -
1.
b1001 /
b1001 1
b1001 @
b0010000 A
#19000000000000
0!
0%
0.
#19500000000000
1!
b0100100 #
b1000000 $
1%
b0100100 '
b1000000 (
1)
b0010 ,
b0000 -
1.
b0000 /
10
b0000 1
13
14
b0010 5
b0010 7
b0000 @
b1000000 A
b0010 B
b0100100 C
#20000000000000
0!
0%
0.
