roteiro_1/disp7.vhd
library IEEE;
use IEEE.STD_LOGIC_1164.ALL;
ENTITY disp7 IS
PORT (dec : IN STD_LOGIC_VECTOR (3 DOWNTO 0);
	disp : OUT STD_LOGIC_VECTOR (6 DOWNTO 0));
END disp7;

ARCHITECTURE decod OF disp7 IS
BEGIN
	with dec select
	disp <= "1111001" when "0001", --1
	"0100100" when "0010", --2
	"0110000" when "0011", --3
	"0011001" when "0100", --4
	"0010010" when "0101", --5
	"0000010" when "0110", --6
	"1111000" when "0111", --7
	"0000000" when "1000", --8
	"0010000" when "1001", --9
	"0001000" when "1010", --A
	"0000011" when "1011", --b
	"1000110" when "1100", --C
	"0100001" when "1101", --d
	"0000110" when "1110", --E
	"0001110" when "1111", --F
	"1000000" when others; --0
END decod;

roteiro_1/conta.vhd
LIBRARY IEEE;
USE IEEE.STD_LOGIC_1164.ALL;
USE IEEE.NUMERIC_STD.ALL;
USE IEEE.MATH_REAL.ALL;

ENTITY conta IS
	PORT ( ckin : IN STD_LOGIC;
	vcont : OUT STD_LOGIC_VECTOR (3 DOWNTO 0);
	ckout : OUT STD_LOGIC);
END conta;

ARCHITECTURE soma OF conta IS
	SIGNAL vcont_s : STD_LOGIC_VECTOR (3 DOWNTO 0) := "0000";
	SIGNAL max : STD_LOGIC_VECTOR (3 DOWNTO 0) := "1001";
	SIGNAL ckout_s : STD_LOGIC := '0';
BEGIN
	vcont <= vcont_s ;
	ckout <= ckout_s;
	PROCESS (ckin)
	BEGIN
		IF ckin'EVENT and ckin = '0' THEN
			IF vcont_s /= max THEN
				vcont_s <= std_logic_vector(unsigned(vcont_s) + 1);
				ckout_s <= '1';
			ELSE
				vcont_s <= "0000";
				ckout_s <= '0';
			END IF;
		END IF;
	END PROCESS;
END soma;

roteiro_1/contador99.vhd
LIBRARY ieee;
USE ieee.std_logic_1164.all;
ENTITY contador99 IS
PORT
( ck : IN STD_LOGIC;
	hex0 : OUT STD_LOGIC_VECTOR(6 DOWNTO 0);
	hex1 : OUT STD_LOGIC_VECTOR(6 DOWNTO 0);
	hex2 : OUT STD_LOGIC_VECTOR(6 DOWNTO 0)
);
END contador99;

ARCHITECTURE contagem OF contador99 IS
COMPONENT conta
	PORT(ckin : IN STD_LOGIC;
	ckout : OUT STD_LOGIC;
	--ckoutdez : OUT STD_LOGIC;
	vcont : OUT STD_LOGIC_VECTOR(3 DOWNTO 0));
END COMPONENT;

COMPONENT disp7
PORT(
	dec : IN STD_LOGIC_VECTOR(3 DOWNTO 0);
	disp : OUT STD_LOGIC_VECTOR(6 DOWNTO 0)
);

END COMPONENT;

SIGNAL ckdez : STD_LOGIC;
SIGNAL ckcent : STD_LOGIC;
SIGNAL cent : STD_LOGIC_VECTOR(3 DOWNTO 0);
SIGNAL dez : STD_LOGIC_VECTOR(3 DOWNTO 0);
SIGNAL uni : STD_LOGIC_VECTOR(3 DOWNTO 0);

BEGIN
	conta_uni : conta
	PORT MAP(ckin => ck,
	ckout => ckdez,
	vcont => uni);

	conta_dez : conta
	PORT MAP(ckin => ckdez,
	ckout => ckcent,
	vcont => dez);
	
	conta_cent : conta
	PORT MAP(ckin => ckcent,
	vcont => cent);

	disp_uni : disp7
	PORT MAP(dec => uni,
	disp => hex2);

	disp_dez : disp7
	PORT MAP(dec => dez,
	disp => hex1);

	disp_cent : disp7
	PORT MAP (dec => cent,
	disp => hex0);

END contagem;

roteiro_1/testbench2.vhd
library IEEE;
use IEEE.STD_LOGIC_1164.ALL;
use std.textio.all;
--use IEEE.numeric_std.all;


ENTITY testbench2 is
END testbench2;

ARCHITECTURE behavioral OF testbench2 IS
	COMPONENT contador99 
		PORT 
		(
			ck : IN STD_LOGIC;
			hex0 : OUT STD_LOGIC_VECTOR(6 DOWNTO 0);
			hex1 : OUT STD_LOGIC_VECTOR(6 DOWNTO 0);
			hex2 : OUT STD_LOGIC_VECTOR(6 DOWNTO 0)
		);
	END COMPONENT;

-- input
SIGNAL ck : STD_LOGIC := '0';
CONSTANT clk_period : TIME := 1 ms;
-- output
SIGNAL hex0 :  STD_LOGIC_VECTOR(6 DOWNTO 0);
SIGNAL hex1 :  STD_LOGIC_VECTOR(6 DOWNTO 0);
SIGNAL hex2 :  STD_LOGIC_VECTOR(6 DOWNTO 0);

FUNCTION decoder(i : IN STD_LOGIC_VECTOR(6 DOWNTO 0) := "0000000")
	return string is
	VARIABLE output : string(1 to 4);
BEGIN
	CASE i IS
		WHEN "1111110" => output := "0x01";
		WHEN "0110000" => output := "0x4F";
		WHEN "1101101" => output := "0x12";
		WHEN others => output := "0xXX";
		return output;
	END CASE;
	return output;
END FUNCTION;

BEGIN

inst : contador99 PORT MAP (
	ck => ck,
	hex0 => hex0,
	hex1 => hex1,
	hex2 => hex2
);


salva_dados : PROCESS(ck)
	file arquivo : text open write_mode is "/home/demo/saida.dat";
	variable linha : line;
	variable dado : string(1 to 4);
	BEGIN
		IF FALLING_EDGE(ck) THEN
			dado := decoder(hex2);
			write(linha, dado);
			hwrite(linha, hex2); -- Use for debug
			writeline(arquivo, linha);
		END IF;
	END PROCESS;
ck <= NOT ck after clk_period/2;	

END behavioral;

roteiro_1/testbench.vcd
$date
  Wed Apr  6 23:20:47 2022
$end
$version
  GHDL v0
$end
$timescale
  1 fs
$end
$scope module standard $end
$upscope $end
$scope module textio $end
$upscope $end
$scope module std_logic_1164 $end
$upscope $end
$scope module numeric_std $end
$upscope $end
$scope module math_real $end
$upscope $end
$scope module testbench2 $end
$var reg 1 ! ck $end
$var reg 7 " hex0[6:0] $end
$var reg 7 # hex1[6:0] $end
$var reg 7 $ hex2[6:0] $end
$scope module inst $end
$var reg 1 % ck $end
$var reg 7 & hex0[6:0] $end
$var reg 7 ' hex1[6:0] $end
$var reg 7 ( hex2[6:0] $end
$var reg 1 ) ckdez $end
$var reg 1 * ckcent $end
$var reg 4 + cent[3:0] $end
$var reg 4 , dez[3:0] $end
$var reg 4 - uni[3:0] $end
$scope module conta_uni $end
$var reg 1 . ckin $end
$var reg 4 / vcont[3:0] $end
$var reg 1 0 ckout $end
$var reg 4 1 vcont_s[3:0] $end
$var reg 4 2 max[3:0] $end
$var reg 1 3 ckout_s $end
$upscope $end
$scope module conta_dez $end
$var reg 1 4 ckin $end
$var reg 4 5 vcont[3:0] $end
$var reg 1 6 ckout $end
$var reg 4 7 vcont_s[3:0] $end
$var reg 4 8 max[3:0] $end
$var reg 1 9 ckout_s $end
$upscope $end
$scope module conta_cent $end
$var reg 1 : ckin $end
$var reg 4 ; vcont[3:0] $end
$var reg 1 < ckout $end
$var reg 4 = vcont_s[3:0] $end
$var reg 4 > max[3:0] $end
$var reg 1 ? ckout_s $end
$upscope $end
$scope module disp_uni $end
$var reg 4 @ dec[3:0] $end
$var reg 7 A disp[6:0] $end
$upscope $end
$scope module disp_dez $end
$var reg 4 B dec[3:0] $end
$var reg 7 C disp[6:0] $end
$upscope $end
$scope module disp_cent $end
$var reg 4 D dec[3:0] $end
$var reg 7 E disp[6:0] $end
$upscope $end
$upscope $end
$upscope $end
$enddefinitions $end
#0
0!
b1111001 "
b1111001 #
b1000000 $
0%
b1111001 &
b1111001 '
b1000000 (
0)
1*
b0001 +
b0001 ,
b0000 -
0.
b0000 /
00
b0000 1
b1001 2
03
04
b0001 5
16
b0001 7
b1001 8
19
1:
b0001 ;
1<
b0001 =
b1001 >
1?
b0000 @
b1000000 A
b0001 B
b1111001 C
b0001 D
b1111001 E
#500000000000
1!
1%
1.
#1000000000000
0!
b1111001 $
0%
b1111001 (
1)
b0001 -
0.
b0001 /
10
b0001 1
13
14
b0001 @
b1111001 A
#1500000000000
1!
1%
1.
#2000000000000
0!
b0100100 $
0%
b0100100 (
b0010 -
0.
b0010 /
b0010 1
b0010 @
b0100100 A
#2500000000000
1!
1%
1.
#3000000000000
0!
b0110000 $
0%
b0110000 (
b0011 -
0.
b0011 /
b0011 1
b0011 @
b0110000 A
#3500000000000
1!
1%
1.
#4000000000000
0!
b0011001 $
0%
b0011001 (
b0100 -
0.
b0100 /
b0100 1
b0100 @
b0011001 A
#4500000000000
1!
1%
1.
#5000000000000
0!
b0010010 $
0%
b0010010 (
b0101 -
0.
b0101 /
b0101 1
b0101 @
b0010010 A
#5500000000000
1!
1%
1.
#6000000000000
0!
b0000010 $
0%
b0000010 (
b0110 -
0.
b0110 /
b0110 1
b0110 @
b0000010 A
#6500000000000
1!
1%
1.
#7000000000000
0!
b1111000 $
0%
b1111000 (
b0111 -
0.
b0111 /
b0111 1
b0111 @
b1111000 A
#7500000000000
1!
1%
1.
#8000000000000
0!
b0000000 $
0%
b0000000 (
b1000 -
0.
b1000 /
b1000 1
b1000 @
b0000000 A
#8500000000000
1!
1%
1.
#9000000000000
0!
b0010000 $
0%
b0010000 (
b1001 -
0.
b1001 /
b1001 1
b1001 @
b0010000 A
#9500000000000
1!
1%
1.
#10000000000000
0!
b0100100 #
b1000000 $
0%
b0100100 '
b1000000 (
0)
b0010 ,
b0000 -
0.
b0000 /
00
b0000 1
03
04
b0010 5
b0010 7
b0000 @
b1000000 A
b0010 B
b0100100 C
#10500000000000
1!
1%
1.
#11000000000000
0!
b1111001 $
0%
b1111001 (
1)
b0001 -
0.
b0001 /
10
b0001 1
13
14
b0001 @
b1111001 A
#11500000000000
1!
1%
1.
#12000000000000
0!
b0100100 $
0%
b0100100 (
b0010 -
0.
b0010 /
b0010 1
b0010 @
b0100100 A
#12500000000000
1!
1%
1.
#13000000000000
0!
b0110000 $
0%
b0110000 (
b0011 -
0.
b0011 /
b0011 1
b0011 @
b0110000 A
#13500000000000
1!
1%
1.
#14000000000000
0!
b0011001 $
0%
b0011001 (
b0100 -
0.
b0100 /
b0100 1
b0100 @
b0011001 A
#14500000000000
1!
1%
1.
#15000000000000
0!
b0010010 $
0%
b0010010 (
b0101 -
0.
b0101 /
b0101 1
b0101 @
b0010010 A
#15500000000000
1!
1%
1.
#16000000000000
0!
b0000010 $
0%
b0000010 (
b0110 -
0.
b0110 /
b0110 1
b0110 @
b0000010 A
#16500000000000
1!
1%
1.
#17000000000000
0!
b1111000 $
0%
b1111000 (
b0111 -
0.
b0111 /
b0111 1
b0111 @
b1111000 A
#17500000000000
1!
1%
1.
#18000000000000
0!
b0000000 $
0%
b0000000 (
b1000 -
0.
b1000 /
b1000 1
b1000 @
b0000000 A
#18500000000000
1!
1%
1.
#19000000000000
0!
b0010000 $
0%
b0010000 (
b1001 -
0.
b1001 /
b1001 1
b1001 @
b0010000 A
#19500000000000
1!
1%
1.
#20000000000000
0!
b0110000 #
b1000000 $
0%
b0110000 '
b1000000 (
0)
b0011 ,
b0000 -
0.
b0000 /
00
b0000 1
03
04
b0011 5
b0011 7
b0000 @
b1000000 A
b0011 B
b0110000 C
#20500000000000
1!
1%
1.
#21000000000000
0!
b1111001 $
0%
b1111001 (
1)
b0001 -
0.
b0001 /
10
b0001 1
13
14
b0001 @
b1111001 A
#21500000000000
1!
1%
1.
#22000000000000
0!
b0100100 $
0%
b0100100 (
b0010 -
0.
b0010 /
b0010 1
b0010 @
b0100100 A
#22500000000000
1!
1%
1.
#23000000000000
0!
b0110000 $
0%
b0110000 (
b0011 -
0.
b0011 /
b0011 1
b0011 @
b0110000 A
#23500000000000
1!
1%
1.
#24000000000000
0!
b0011001 $
0%
b0011001 (
b0100 -
0.
b0100 /
b0100 1
b0100 @
b0011001 A
#24500000000000
1!
1%
1.
#25000000000000
0!
b0010010 $
0%
b0010010 (
b0101 -
0.
b0101 /
b0101 1
b0101 @
b0010010 A
#25500000000000
1!
1%
1.
#26000000000000
0!
b0000010 $
0%
b0000010 (
b0110 -
0.
b0110 /
b0110 1
b0110 @
b0000010 A
#26500000000000
1!
1%
1.
#27000000000000
0!
b1111000 $
0%
b1111000 (
b0111 -
0.
b0111 /
b0111 1
b0111 @
b1111000 A
#27500000000000
1!
1%
1.
#28000000000000
0!
b0000000 $
0%
b0000000 (
b1000 -
0.
b1000 /
b1000 1
b1000 @
b0000000 A
#28500000000000
1!
1%
1.
#29000000000000
0!
b0010000 $
0%
b0010000 (
b1001 -
0.
b1001 /
b1001 1
b1001 @
b0010000 A
#29500000000000
1!
1%
1.
#30000000000000
0!
b0011001 #
b1000000 $
0%
b0011001 '
b1000000 (
0)
b0100 ,
b0000 -
0.
b0000 /
00
b0000 1
03
04
b0100 5
b0100 7
b0000 @
b1000000 A
b0100 B
b0011001 C
#30500000000000
1!
1%
1.
#31000000000000
0!
b1111001 $
0%
b1111001 (
1)
b0001 -
0.
b0001 /
10
b0001 1
13
14
b0001 @
b1111001 A
#31500000000000
1!
1%
1.
#32000000000000
0!
b0100100 $
0%
b0100100 (
b0010 -
0.
b0010 /
b0010 1
b0010 @
b0100100 A
#32500000000000
1!
1%
1.
#33000000000000
0!
b0110000 $
0%
b0110000 (
b0011 -
0.
b0011 /
b0011 1
b0011 @
b0110000 A
#33500000000000
1!
1%
1.
#34000000000000
0!
b0011001 $
0%
b0011001 (
b0100 -
0.
b0100 /
b0100 1
b0100 @
b0011001 A
#34500000000000
1!
1%
1.
#35000000000000
0!
b0010010 $
0%
b0010010 (
b0101 -
0.
b0101 /
b0101 1
b0101 @
b0010010 A
#35500000000000
1!
1%
1.
#36000000000000
0!
b0000010 $
0%
b0000010 (
b0110 -
0.
b0110 /
b0110 1
b0110 @
b0000010 A
#36500000000000
1!
1%
1.
#37000000000000
0!
b1111000 $
0%
b1111000 (
b0111 -
0.
b0111 /
b0111 1
b0111 @
b1111000 A
#37500000000000
1!
1%
1.
#38000000000000
0!
b0000000 $
0%
b0000000 (
b1000 -
0.
b1000 /
b1000 1
b1000 @
b0000000 A
#38500000000000
1!
1%
1.
#39000000000000
0!
b0010000 $
0%
b0010000 (
b1001 -
0.
b1001 /
b1001 1
b1001 @
b0010000 A
#39500000000000
1!
1%
1.
#40000000000000
0!
b0010010 #
b1000000 $
0%
b0010010 '
b1000000 (
0)
b0101 ,
b0000 -
0.
b0000 /
00
b0000 1
03
04
b0101 5
b0101 7
b0000 @
b1000000 A
b0101 B
b0010010 C
#40500000000000
1!
1%
1.
#41000000000000
0!
b1111001 $
0%
b1111001 (
1)
b0001 -
0.
b0001 /
10
b0001 1
13
14
b0001 @
b1111001 A
#41500000000000
1!
1%
1.
#42000000000000
0!
b0100100 $
0%
b0100100 (
b0010 -
0.
b0010 /
b0010 1
b0010 @
b0100100 A
#42500000000000
1!
1%
1.
#43000000000000
0!
b0110000 $
0%
b0110000 (
b0011 -
0.
b0011 /
b0011 1
b0011 @
b0110000 A
#43500000000000
1!
1%
1.
#44000000000000
0!
b0011001 $
0%
b0011001 (
b0100 -
0.
b0100 /
b0100 1
b0100 @
b0011001 A
#44500000000000
1!
1%
1.
#45000000000000
0!
b0010010 $
0%
b0010010 (
b0101 -
0.
b0101 /
b0101 1
b0101 @
b0010010 A
#45500000000000
1!
1%
1.
#46000000000000
0!
b0000010 $
0%
b0000010 (
b0110 -
0.
b0110 /
b0110 1
b0110 @
b0000010 A
#46500000000000
1!
1%
1.
#47000000000000
0!
b1111000 $
0%
b1111000 (
b0111 -
0.
b0111 /
b0111 1
b0111 @
b1111000 A
#47500000000000
1!
1%
1.
#48000000000000
0!
b0000000 $
0%
b0000000 (
b1000 -
0.
b1000 /
b1000 1
b1000 @
b0000000 A
#48500000000000
1!
1%
1.
#49000000000000
0!
b0010000 $
0%
b0010000 (
b1001 -
0.
b1001 /
b1001 1
b1001 @
b0010000 A
#49500000000000
1!
1%
1.
#50000000000000
0!
b0000010 #
b1000000 $
0%
b0000010 '
b1000000 (
0)
b0110 ,
b0000 -
0.
b0000 /
00
b0000 1
03
04
b0110 5
b0110 7
b0000 @
b1000000 A
b0110 B
b0000010 C
#50500000000000
1!
1%
1.
#51000000000000
0!
b1111001 $
0%
b1111001 (
1)
b0001 -
0.
b0001 /
10
b0001 1
13
14
b0001 @
b1111001 A
#51500000000000
1!
1%
1.
#52000000000000
0!
b0100100 $
0%
b0100100 (
b0010 -
0.
b0010 /
b0010 1
b0010 @
b0100100 A
#52500000000000
1!
1%
1.
#53000000000000
0!
b0110000 $
0%
b0110000 (
b0011 -
0.
b0011 /
b0011 1
b0011 @
b0110000 A
#53500000000000
1!
1%
1.
#54000000000000
0!
b0011001 $
0%
b0011001 (
b0100 -
0.
b0100 /
b0100 1
b0100 @
b0011001 A
#54500000000000
1!
1%
1.
#55000000000000
0!
b0010010 $
0%
b0010010 (
b0101 -
0.
b0101 /
b0101 1
b0101 @
b0010010 A
#55500000000000
1!
1%
1.
#56000000000000
0!
b0000010 $
0%
b0000010 (
b0110 -
0.
b0110 /
b0110 1
b0110 @
b0000010 A
#56500000000000
1!
1%
1.
#57000000000000
0!
b1111000 $
0%
b1111000 (
b0111 -
0.
b0111 /
b0111 1
b0111 @
b1111000 A
#57500000000000
1!
1%
1.
#58000000000000
0!
b0000000 $
0%
b0000000 (
b1000 -
0.
b1000 /
b1000 1
b1000 @
b0000000 A
#58500000000000
1!
1%
1.
#59000000000000
0!
b0010000 $
0%
b0010000 (
b1001 -
0.
b1001 /
b1001 1
b1001 @
b0010000 A
#59500000000000
1!
1%
1.
#60000000000000
0!
b1111000 #
b1000000 $
0%
b1111000 '
b1000000 (
0)
b0111 ,
b0000 -
0.
b0000 /
00
b0000 1
03
04
b0111 5
b0111 7
b0000 @
b1000000 A
b0111 B
b1111000 C
#60500000000000
1!
1%
1.
#61000000000000
0!
b1111001 $
0%
b1111001 (
1)
b0001 -
0.
b0001 /
10
b0001 1
13
14
b0001 @
b1111001 A
#61500000000000
1!
1%
1.
#62000000000000
0!
b0100100 $
0%
b0100100 (
b0010 -
0.
b0010 /
b0010 1
b0010 @
b0100100 A
#62500000000000
1!
1%
1.
#63000000000000
0!
b0110000 $
0%
b0110000 (
b0011 -
0.
b0011 /
b0011 1
b0011 @
b0110000 A
#63500000000000
1!
1%
1.
#64000000000000
0!
b0011001 $
0%
b0011001 (
b0100 -
0.
b0100 /
b0100 1
b0100 @
b0011001 A
#64500000000000
1!
1%
1.
#65000000000000
0!
b0010010 $
0%
b0010010 (
b0101 -
0.
b0101 /
b0101 1
b0101 @
b0010010 A
#65500000000000
1!
1%
1.
#66000000000000
0!
b0000010 $
0%
b0000010 (
b0110 -
0.
b0110 /
b0110 1
b0110 @
b0000010 A
#66500000000000
1!
1%
1.
#67000000000000
0!
b1111000 $
0%
b1111000 (
b0111 -
0.
b0111 /
b0111 1
b0111 @
b1111000 A
#67500000000000
1!
1%
1.
#68000000000000
0!
b0000000 $
0%
b0000000 (
b1000 -
0.
b1000 /
b1000 1
b1000 @
b0000000 A
#68500000000000
1!
1%
1.
#69000000000000
0!
b0010000 $
0%
b0010000 (
b1001 -
0.
b1001 /
b1001 1
b1001 @
b0010000 A
#69500000000000
1!
1%
1.
#70000000000000
0!
b0000000 #
b1000000 $
0%
b0000000 '
b1000000 (
0)
b1000 ,
b0000 -
0.
b0000 /
00
b0000 1
03
04
b1000 5
b1000 7
b0000 @
b1000000 A
b1000 B
b0000000 C
#70500000000000
1!
1%
1.
#71000000000000
0!
b1111001 $
0%
b1111001 (
1)
b0001 -
0.
b0001 /
10
b0001 1
13
14
b0001 @
b1111001 A
#71500000000000
1!
1%
1.
#72000000000000
0!
b0100100 $
0%
b0100100 (
b0010 -
0.
b0010 /
b0010 1
b0010 @
b0100100 A
#72500000000000
1!
1%
1.
#73000000000000
0!
b0110000 $
0%
b0110000 (
b0011 -
0.
b0011 /
b0011 1
b0011 @
b0110000 A
#73500000000000
1!
1%
1.
#74000000000000
0!
b0011001 $
0%
b0011001 (
b0100 -
0.
b0100 /
b0100 1
b0100 @
b0011001 A
#74500000000000
1!
1%
1.
#75000000000000
0!
b0010010 $
0%
b0010010 (
b0101 -
0.
b0101 /
b0101 1
b0101 @
b0010010 A
#75500000000000
1!
1%
1.
#76000000000000
0!
b0000010 $
0%
b0000010 (
b0110 -
0.
b0110 /
b0110 1
b0110 @
b0000010 A
#76500000000000
1!
1%
1.
#77000000000000
0!
b1111000 $
0%
b1111000 (
b0111 -
0.
b0111 /
b0111 1
b0111 @
b1111000 A
#77500000000000
1!
1%
1.
#78000000000000
0!
b0000000 $
0%
b0000000 (
b1000 -
0.
b1000 /
b1000 1
b1000 @
b0000000 A
#78500000000000
1!
1%
1.
#79000000000000
0!
b0010000 $
0%
b0010000 (
b1001 -
0.
b1001 /
b1001 1
b1001 @
b0010000 A
#79500000000000
1!
1%
1.
#80000000000000
0!
b0010000 #
b1000000 $
0%
b0010000 '
b1000000 (
0)
b1001 ,
b0000 -
0.
b0000 /
00
b0000 1
03
04
b1001 5
b1001 7
b0000 @
b1000000 A
b1001 B
b0010000 C
#80500000000000
1!
1%
1.
#81000000000000
0!
b1111001 $
0%
b1111001 (
1)
b0001 -
0.
b0001 /
10
b0001 1
13
14
b0001 @
b1111001 A
#81500000000000
1!
1%
1.
#82000000000000
0!
b0100100 $
0%
b0100100 (
b0010 -
0.
b0010 /
b0010 1
b0010 @
b0100100 A
#82500000000000
1!
1%
1.
#83000000000000
0!
b0110000 $
0%
b0110000 (
b0011 -
0.
b0011 /
b0011 1
b0011 @
b0110000 A
#83500000000000
1!
1%
1.
#84000000000000
0!
b0011001 $
0%
b0011001 (
b0100 -
0.
b0100 /
b0100 1
b0100 @
b0011001 A
#84500000000000
1!
1%
1.
#85000000000000
0!
b0010010 $
0%
b0010010 (
b0101 -
0.
b0101 /
b0101 1
b0101 @
b0010010 A
#85500000000000
1!
1%
1.
#86000000000000
0!
b0000010 $
0%
b0000010 (
b0110 -
0.
b0110 /
b0110 1
b0110 @
b0000010 A
#86500000000000
1!
1%
1.
#87000000000000
0!
b1111000 $
0%
b1111000 (
b0111 -
0.
b0111 /
b0111 1
b0111 @
b1111000 A
#87500000000000
1!
1%
1.
#88000000000000
0!
b0000000 $
0%
b0000000 (
b1000 -
0.
b1000 /
b1000 1
b1000 @
b0000000 A
#88500000000000
1!
1%
1.
#89000000000000
0!
b0010000 $
0%
b0010000 (
b1001 -
0.
b1001 /
b1001 1
b1001 @
b0010000 A
#89500000000000
1!
1%
1.
#90000000000000
0!
b0100100 "
b1000000 #
b1000000 $
0%
b0100100 &
b1000000 '
b1000000 (
0)
0*
b0010 +
b0000 ,
b0000 -
0.
b0000 /
00
b0000 1
03
04
b0000 5
06
b0000 7
09
0:
b0010 ;
b0010 =
b0000 @
b1000000 A
b0000 B
b1000000 C
b0010 D
b0100100 E
#90500000000000
1!
1%
1.
#91000000000000
0!
b1111001 $
0%
b1111001 (
1)
b0001 -
0.
b0001 /
10
b0001 1
13
14
b0001 @
b1111001 A
#91500000000000
1!
1%
1.
#92000000000000
0!
b0100100 $
0%
b0100100 (
b0010 -
0.
b0010 /
b0010 1
b0010 @
b0100100 A
#92500000000000
1!
1%
1.
#93000000000000
0!
b0110000 $
0%
b0110000 (
b0011 -
0.
b0011 /
b0011 1
b0011 @
b0110000 A
#93500000000000
1!
1%
1.
#94000000000000
0!
b0011001 $
0%
b0011001 (
b0100 -
0.
b0100 /
b0100 1
b0100 @
b0011001 A
#94500000000000
1!
1%
1.
#95000000000000
0!
b0010010 $
0%
b0010010 (
b0101 -
0.
b0101 /
b0101 1
b0101 @
b0010010 A
#95500000000000
1!
1%
1.
#96000000000000
0!
b0000010 $
0%
b0000010 (
b0110 -
0.
b0110 /
b0110 1
b0110 @
b0000010 A
#96500000000000
1!
1%
1.
#97000000000000
0!
b1111000 $
0%
b1111000 (
b0111 -
0.
b0111 /
b0111 1
b0111 @
b1111000 A
#97500000000000
1!
1%
1.
#98000000000000
0!
b0000000 $
0%
b0000000 (
b1000 -
0.
b1000 /
b1000 1
b1000 @
b0000000 A
#98500000000000
1!
1%
1.
#99000000000000
0!
b0010000 $
0%
b0010000 (
b1001 -
0.
b1001 /
b1001 1
b1001 @
b0010000 A
#99500000000000
1!
1%
1.
#100000000000000
0!
b1111001 #
b1000000 $
0%
b1111001 '
b1000000 (
0)
1*
b0001 ,
b0000 -
0.
b0000 /
00
b0000 1
03
04
b0001 5
16
b0001 7
19
1:
b0000 @
b1000000 A
b0001 B
b1111001 C
